Workbook

Sheet Opearating Model
A2: x | B2: EFN Operating Model
D4: 365 | E4: 366 | F4: 90 | G4: 91 | H4: 92 | I4: 92 | J4: 365 | K4: 90 | L4: 91 | M4: 92 | N4: 92 | O4: 365 | P4: 90 | Q4: 91 | R4: 92 | S4: 92 | T4: 365 | U4: 366 | V4: 365 | W4: 365
A5: x | B5: Operating Model | C5: Units | D5: 2023 | E5: =D5+1 -> 2024 | F5: Q1'25A | G5: Q2'25A | H5: Q3'25A | I5: Q4'25A | J5: =E5+1 -> 2025 | K5: Q1'26A | L5: Q2'26E | M5: Q3'26E | N5: Q4'26E | O5: =J5+1 -> 2026 | P5: Q1'27E | Q5: Q2'27E | R5: Q3'27E | S5: Q4'27E | T5: =O5+1 -> 2027 | U5: =T5+1 -> 2028 | V5: =U5+1 -> 2029 | W5: =V5+1 -> 2030
B7: Interest Income | C7: $ | D7: ='Revenue Build'!D50 -> 521.50274 | E7: ='Revenue Build'!E50 -> 628.583 | F7: ='Revenue Build'!F50 -> 146.723 | G7: ='Revenue Build'!G50 -> 155.329 | H7: ='Revenue Build'!H50 -> 161.211 | I7: ='Revenue Build'!I50 -> 150.758 | J7: ='Revenue Build'!J50 -> 614.021 | K7: ='Revenue Build'!K50 -> 152.905 | ... W7: ='Revenue Build'!W50 -> 789.5524
B8: Rental Revenue | C8: $ | D8: ='Revenue Build'!D53 -> 803.28445 | E8: ='Revenue Build'!E53 -> 897.311 | F8: ='Revenue Build'!F53 -> 223.255 | G8: ='Revenue Build'!G53 -> 244.844 | H8: ='Revenue Build'!H53 -> 254.166 | I8: ='Revenue Build'!I53 -> 258.84 | J8: ='Revenue Build'!J53 -> 981.105 | K8: ='Revenue Build'!K53 -> 283.732 | ... W8: ='Revenue Build'!W53 -> 1466.0161
B9: Depreciation of equipment under operating leases | C9: $ | D9: ='Revenue Build'!D56 -> -483.40159 | E9: ='Revenue Build'!E56 -> -523.44 | F9: ='Revenue Build'!F56 -> -130.208 | G9: ='Revenue Build'!G56 -> -140.554 | H9: ='Revenue Build'!H56 -> -150.066 | I9: ='Revenue Build'!I56 -> -152.284 | J9: ='Revenue Build'!J56 -> -573.112 | K9: ='Revenue Build'!K56 -> -170.106 | ... W9: ='Revenue Build'!W56 -> -840.424
B10: Interest Expense | C10: $ | D10: ='Revenue Build'!D57 -> -430.67053 | E10: ='Revenue Build'!E57 -> -553.324 | F10: ='Revenue Build'!F57 -> -128.214 | G10: ='Revenue Build'!G57 -> -132.537 | H10: ='Revenue Build'!H57 -> -135.103 | I10: ='Revenue Build'!I57 -> -127.843 | J10: ='Revenue Build'!J57 -> -523.697 | K10: ='Revenue Build'!K57 -> -129.013 | ... W10: ='Revenue Build'!W57 -> -719.40548
B11: Net Financing Revenue | C11: $ | D11: =SUM(D7:D10) -> 410.71508 | E11: =SUM(E7:E10) -> 449.13 | F11: =SUM(F7:F10) -> 111.556 | G11: =SUM(G7:G10) -> 127.082 | H11: =SUM(H7:H10) -> 130.208 | I11: =SUM(I7:I10) -> 129.471 | J11: =SUM(J7:J10) -> 498.317 | K11: =SUM(K7:K10) -> 137.518 | ... W11: =SUM(W7:W10) -> 695.73906
B13: Service and Other Revenue, net | C13: $ | D13: ='Revenue Build'!D27 -> 502.43179 | E13: ='Revenue Build'!E27 -> 595.54 | F13: ='Revenue Build'!F27 -> 152.482 | G13: ='Revenue Build'!G27 -> 151.336 | H13: ='Revenue Build'!H27 -> 156.17 | I13: ='Revenue Build'!I27 -> 162.864 | J13: ='Revenue Build'!J27 -> 622.852 | K13: ='Revenue Build'!K27 -> 162.125 | ... W13: ='Revenue Build'!W27 -> 1011.2992
B15: Syndication Revenue | C15: $ | D15: ='Revenue Build'!D64 -> 45.553521 | E15: ='Revenue Build'!E64 -> 42.89 | F15: ='Revenue Build'!F64 -> 11.633 | G15: ='Revenue Build'!G64 -> 11.608 | H15: ='Revenue Build'!H64 -> 20.012 | I15: ='Revenue Build'!I64 -> 21.088 | J15: ='Revenue Build'!J64 -> 64.341 | K15: ='Revenue Build'!K64 -> 23.873 | ... W15: ='Revenue Build'!W64 -> 80
A17: x | B17: Net Revenue | C17: $ | D17: =D15+D13+D11 -> 958.70039 | E17: =E15+E13+E11 -> 1087.56 | F17: =F15+F13+F11 -> 275.671 | G17: =G15+G13+G11 -> 290.026 | H17: =H15+H13+H11 -> 306.39 | I17: =I15+I13+I11 -> 313.423 | J17: =J15+J13+J11 -> 1185.51 | K17: =K15+K13+K11 -> 323.516 | ... W17: =W15+W13+W11 -> 1787.0382
B18: % y/y change | C18: % | D18: 0 | E18: =E17/D17-1 -> 0.13441072 | F18: 0 | G18: 0 | H18: 0 | I18: 0 | J18: =J17/E17-1 -> 0.090063996 | K18: =K17/F17-1 -> 0.17355834 | L18: =L17/G17-1 -> 0.078172044 | M18: =M17/H17-1 -> 0.096636667 | N18: =N17/I17-1 -> 0.086318687 | O18: =O17/J17-1 -> 0.10727847 | P18: =P17/K17-1 -> -0.0042564063 | Q18: =Q17/L17-1 -> 0.099020244 | ... T18: =T17/O17-1 -> 0.074203133 | U18: =U17/T17-1 -> 0.086137867 | V18: =V17/U17-1 -> 0.086237166 | W18: =W17/V17-1 -> 0.074176724
B20: Salaries, wages and benefits | C20: $ | D20: 271.71954 | E20: 303.602 | F20: 74.884 | G20: 73.94 | H20: 78.386 | I20: 89.013 | J20: =SUM(F20:I20) -> 316.223 | K20: 94.071 | L20: =L17*L21 -> 81.301461 | M20: =M17*M21 -> 87.359612 | N20: =N17*N21 -> 88.524088 | O20: =SUM(K20:N20) -> 351.25616 | P20: =P17*P21 -> 83.756136 | Q20: =Q17*Q21 -> 89.351951 | R20: =R17*R21 -> 95.61501 | S20: =S17*S21 -> 96.051125 | T20: =SUM(P20:S20) -> 364.77422 | U20: =U17*U21 -> 396.1951 | V20: =V17*V21 -> 430.36184 | W20: =W17*W21 -> 462.28467
B21: % revenue | C21: % | D21: =D20/D17 -> 0.28342487 | E21: =E20/E17 -> 0.27915885 | F21: =F20/F17 -> 0.27164265 | G21: =G20/G17 -> 0.25494266 | H21: =H20/H17 -> 0.25583733 | I21: =I20/I17 -> 0.28400277 | J21: =J20/J17 -> 0.26674005 | K21: =K20/K17 -> 0.29077696 | L21: 0.26 | M21: =L21 -> 0.26 | N21: =M21 -> 0.26 | O21: =O20/O17 -> 0.26758507 | P21: =L21 -> 0.26 | Q21: =L21 -> 0.26 | R21: =M21 -> 0.26 | S21: =N21 -> 0.26 | T21: =T20/T17 -> 0.25868762 | U21: =T21 -> 0.25868762 | V21: =U21 -> 0.25868762 | W21: =V21 -> 0.25868762
B23: General and administration expenses | C23: $ | D23: 119.05712 | E23: 136.706 | F23: 34.167 | G23: 37.921 | H23: 35.594 | I23: 45.162 | J23: =SUM(F23:I23) -> 152.844 | K23: 37.039 | L23: =L17*L24 -> 37.523751 | M23: =M17*M24 -> 40.319821 | N23: =N17*N24 -> 40.857271 | O23: =SUM(K23:N23) -> 155.73984 | P23: =P17*P24 -> 38.656678 | Q23: =Q17*Q24 -> 41.239362 | R23: =R17*R24 -> 44.130005 | S23: =S17*S24 -> 44.331289 | T23: =SUM(P23:S23) -> 168.35733 | U23: =T23 -> 168.35733 | V23: =U23 -> 168.35733 | W23: =V23 -> 168.35733
B24: % revenue | C24: % | D24: =D23/D17 -> 0.12418596 | E24: =E23/E17 -> 0.12569973 | F24: =F23/F17 -> 0.12394122 | G24: =G23/G17 -> 0.13075035 | H24: =H23/H17 -> 0.1161722 | I24: =I23/I17 -> 0.14409281 | J24: =J23/J17 -> 0.12892679 | K24: =K23/K17 -> 0.11448893 | L24: 0.12 | M24: =L24 -> 0.12 | N24: =M24 -> 0.12 | O24: =O23/O17 -> 0.11864178 | P24: =L24 -> 0.12 | Q24: =L24 -> 0.12 | R24: =M24 -> 0.12 | S24: =N24 -> 0.12 | T24: =T23/T17 -> 0.11939429 | U24: =T24 -> 0.11939429 | V24: =U24 -> 0.11939429 | W24: =V24 -> 0.11939429
B26: Depreciation and amortization | C26: $ | D26: 51.336884 | E26: 59.421 | F26: 15.773 | G26: 16.315 | H26: 16.75 | I26: 71.267 | J26: =SUM(F26:I26) -> 120.105 | K26: 17.027 | L26: =L17*L27 -> 17.198386 | M26: =M17*M27 -> 18.479918 | N26: =N17*N27 -> 18.726249 | O26: =SUM(K26:N26) -> 71.431553 | P26: =P17*P27 -> 17.717644 | Q26: =Q17*Q27 -> 18.901374 | R26: =R17*R27 -> 20.226252 | S26: =S17*S27 -> 20.318507 | T26: =SUM(P26:S26) -> 77.163778 | U26: =U17*U27 -> 83.810501 | V26: =V17*V27 -> 91.038081 | W26: =W17*W27 -> 97.790988
B27: % revenue | C27: % | D27: =D26/D17 -> 0.053548413 | E27: =E26/E17 -> 0.054636986 | F27: =F26/F17 -> 0.057216755 | G27: =G26/G17 -> 0.056253577 | H27: =H26/H17 -> 0.054668886 | I27: =I26/I17 -> 0.2273828 | J27: =J26/J17 -> 0.10131083 | K27: =K26/K17 -> 0.052631091 | L27: 0.055 | M27: =L27 -> 0.055 | N27: =M27 -> 0.055 | O27: =O26/O17 -> 0.054416176 | P27: =L27 -> 0.055 | Q27: =P27 -> 0.055 | R27: =Q27 -> 0.055 | S27: =R27 -> 0.055 | T27: =T26/T17 -> 0.054722382 | U27: =T27 -> 0.054722382 | V27: =U27 -> 0.054722382 | W27: =V27 -> 0.054722382
B29: Amortization of convertible debenture synthetic discount | C29: $ | D29: 3.0372471 | E29: 1.517 | F29: 0 | G29: 0 | H29: 0 | I29: 0 | J29: =SUM(F29:I29) -> 0 | K29: 0 | L29: =K29 -> 0 | M29: =L29 -> 0 | N29: =M29 -> 0 | O29: =SUM(K29:N29) -> 0 | P29: =K29 -> 0 | Q29: =L29 -> 0 | R29: =M29 -> 0 | S29: =N29 -> 0 | T29: =SUM(P29:S29) -> 0 | U29: =T29 -> 0 | V29: =U29 -> 0 | W29: =V29 -> 0
B30: % revenue | C30: % | D30: =D29/D17 -> 0.0031680879 | E30: =E29/E17 -> 0.0013948656 | F30: =F29/F17 -> 0 | G30: =G29/G17 -> 0 | H30: =H29/H17 -> 0 | I30: =I29/I17 -> 0 | J30: =J29/J17 -> 0 | K30: =K29/K17 -> 0 | ... W30: =W29/W17 -> 0
B32: Share-based compensation | C32: $ | D32: 36.470671 | E32: 43.435 | F32: 10.183 | G32: 10.333 | H32: 8.252 | I32: 10.75 | J32: =SUM(F32:I32) -> 39.518 | K32: 9.335 | L32: =L17*L33 -> 10.957625 | M32: =M17*M33 -> 11.774128 | N32: =N17*N33 -> 11.931074 | O32: =SUM(K32:N32) -> 43.997827 | P32: =P17*P33 -> 11.28846 | Q32: =Q17*Q33 -> 12.042651 | R32: =R17*R33 -> 12.886772 | S32: =S17*S33 -> 12.945551 | T32: =SUM(P32:S32) -> 49.163434 | U32: =U17*U33 -> 53.398267 | V32: =V17*V33 -> 58.003183 | W32: =W17*W33 -> 62.305669
B33: % revenue | C33: % | D33: =D32/D17 -> 0.038041782 | E33: =E32/E17 -> 0.039938026 | F33: =F32/F17 -> 0.03693896 | G33: =G32/G17 -> 0.03562784 | H33: =H32/H17 -> 0.026932994 | I33: =I32/I17 -> 0.034298695 | J33: =J32/J17 -> 0.033334177 | K33: =K32/K17 -> 0.028854833 | L33: =AVERAGE(J33:K33, D33:E33) -> 0.035042204 | M33: =L33 -> 0.035042204 | N33: =M33 -> 0.035042204 | O33: =O32/O17 -> 0.033517309 | P33: =L33 -> 0.035042204 | Q33: =P33 -> 0.035042204 | R33: =Q33 -> 0.035042204 | S33: =R33 -> 0.035042204 | T33: =T32/T17 -> 0.034865325 | U33: =T33 -> 0.034865325 | V33: =U33 -> 0.034865325 | W33: =V33 -> 0.034865325
A35: x | B35: Operating Income | C35: $ | D35: =D17-SUM(D20,D23,D26,D29,D32) -> 477.07893 | E35: =E17-SUM(E20,E23,E26,E29,E32) -> 542.879 | F35: =F17-SUM(F20,F23,F26,F29,F32) -> 140.664 | G35: =G17-SUM(G20,G23,G26,G29,G32) -> 151.517 | H35: =H17-SUM(H20,H23,H26,H29,H32) -> 167.408 | I35: =I17-SUM(I20,I23,I26,I29,I32) -> 97.231 | J35: =J17-SUM(J20,J23,J26,J29,J32) -> 556.82 | K35: =K17-SUM(K20,K23,K26,K29,K32) -> 166.044 | ... W35: =W17-SUM(W20,W23,W26,W29,W32) -> 996.29956
B36: % y/y change | C36: % | D36: 0 | E36: =E35/D35-1 -> 0.13792282 | F36: 0 | G36: 0 | H36: 0 | I36: 0 | J36: =J35/E35-1 -> 0.025679756 | K36: =K35/F35-1 -> 0.18042996 | L36: =L35/G35-1 -> 0.093716897 | M36: =M35/H35-1 -> 0.063659017 | N36: =N35/I35-1 -> 0.85577212 | O36: =O35/J35-1 -> 0.23965431 | P36: =P35/K35-1 -> 0.028161608 | Q36: =Q35/L35-1 -> 0.099020244 | ... T36: =T35/O35-1 -> 0.087462591 | U36: =U35/T35-1 -> 0.10545739 | V36: =V35/U35-1 -> 0.10373381 | W36: =W35/V35-1 -> 0.087811989
B37: % EBIT margin | C37: % | D37: =D35/D17 -> 0.49763089 | E37: =E35/E17 -> 0.49917154 | F37: =F35/F17 -> 0.51026042 | G37: =G35/G17 -> 0.52242558 | H37: =H35/H17 -> 0.54638859 | I37: =I35/I17 -> 0.31022293 | J37: =J35/J17 -> 0.46968815 | K37: =K35/K17 -> 0.51324819 | ... W37: =W35/W17 -> 0.55751441
B39: Amortization of intangibles assets from acquisitions | C39: $ | D39: 27.903412 | E39: 28.734 | F39: 7.799 | G39: 7.829 | H39: 7.831 | I39: 7.823 | J39: =SUM(F39:I39) -> 31.282 | K39: 8.979 | L39: =L17*L40 -> 8.6787506 | M39: =M17*M40 -> 9.3254448 | N39: =N17*N40 -> 9.44975 | O39: =SUM(K39:N39) -> 36.432945 | P39: =P17*P40 -> 8.9407817 | Q39: =Q17*Q40 -> 9.5381226 | R39: =R17*R40 -> 10.20669 | S39: =S17*S40 -> 10.253245 | T39: =SUM(P39:S39) -> 38.938839 | U39: =U17*U40 -> 42.292948 | V39: =V17*V40 -> 45.940172 | W39: =W17*W40 -> 49.347863
B40: % revenue | C40: % | D40: =D39/D17 -> 0.029105456 | E40: =E39/E17 -> 0.026420611 | F40: =F39/F17 -> 0.02829097 | G40: =G39/G17 -> 0.026994132 | H40: =H39/H17 -> 0.025558928 | I40: =I39/I17 -> 0.024959879 | J40: =J39/J17 -> 0.026386956 | K40: =K39/K17 -> 0.027754423 | L40: =K40 -> 0.027754423 | M40: =L40 -> 0.027754423 | N40: =M40 -> 0.027754423 | O40: =O39/O17 -> 0.027754423 | P40: =K40 -> 0.027754423 | Q40: =P40 -> 0.027754423 | R40: =Q40 -> 0.027754423 | S40: =R40 -> 0.027754423 | T40: =T39/T17 -> 0.02761433 | U40: =T40 -> 0.02761433 | V40: =U40 -> 0.02761433 | W40: =V40 -> 0.02761433
B42: Gain on investments | C42: $ | D42: 0 | E42: 0 | F42: -3.606 | G42: 0 | H42: 0 | I42: 3.606 | J42: =SUM(F42:I42) -> 0 | K42: 0.083 | L42: 0 | M42: 0 | N42: 0 | O42: =SUM(K42:N42) -> 0.083 | P42: =L42 -> 0 | Q42: =P42 -> 0 | R42: =Q42 -> 0 | S42: =R42 -> 0 | T42: =SUM(P42:S42) -> 0 | U42: =T42 -> 0 | V42: =U42 -> 0 | W42: =V42 -> 0
B43: % revenue | C43: %
B45: Share loss from provision in equity accounted investments | C45: $ | D45: 0.50892409 | E45: 0.588 | F45: 0 | G45: 0.238 | H45: -0.087 | I45: -3.932 | J45: =SUM(F45:I45) -> -3.781 | K45: 0 | L45: =K45 -> 0 | M45: =L45 -> 0 | N45: =M45 -> 0 | O45: =SUM(K45:N45) -> 0 | P45: =K45 -> 0 | Q45: =P45 -> 0 | R45: =Q45 -> 0 | S45: =R45 -> 0 | T45: =SUM(P45:S45) -> 0 | U45: =T45 -> 0 | V45: =U45 -> 0 | W45: =V45 -> 0
B46: % revenue | C46: %
A48: x | B48: Income Before Taxes (EBT) | C48: $ | D48: =D35-SUM(D39,D42,D45) -> 448.66659 | E48: =E35-SUM(E39,E42,E45) -> 513.557 | F48: =F35-SUM(F39,F42,F45) -> 136.471 | G48: =G35-SUM(G39,G42,G45) -> 143.45 | H48: =H35-SUM(H39,H42,H45) -> 159.664 | I48: =I35-SUM(I39,I42,I45) -> 89.734 | J48: =J35-SUM(J39,J42,J45) -> 529.319 | K48: =K35-SUM(K39,K42,K45) -> 156.982 | ... W48: =W35-SUM(W39,W42,W45) -> 946.9517
B49: % y/y change | C49: % | D49: 0 | E49: =E48/D48-1 -> 0.14462946 | F49: 0 | G49: 0 | H49: 0 | I49: 0 | J49: =J48/E48-1 -> 0.030691822 | K49: =K48/F48-1 -> 0.15029567 | L49: =L48/G48-1 -> 0.094722569 | M49: =M48/H48-1 -> 0.056841767 | N49: =N48/I48-1 -> 0.90550771 | O49: =O48/J48-1 -> 0.23507444 | P49: =P48/K48-1 -> 0.030559455 | Q49: =Q48/L48-1 -> 0.099020244 | ... T49: =T48/O48-1 -> 0.088641769 | U49: =U48/T48-1 -> 0.10651441 | V49: =V48/U48-1 -> 0.10467347 | W49: =W48/V48-1 -> 0.088532051
B50: % margin | C50: % | D50: =D48/D35 -> 0.94044521 | E50: =E48/E35 -> 0.94598796 | F50: =F48/F35 -> 0.97019138 | G50: =G48/G35 -> 0.94675845 | H50: =H48/H35 -> 0.95374176 | I50: =I48/I35 -> 0.92289496 | J50: =J48/J35 -> 0.95061061 | K50: =K48/K35 -> 0.9454241 | ... W50: =W48/W35 -> 0.95046885
B52: Income Tax Expense | C52: $ | D52: 103.31159 | E52: 126.42 | F52: 34.221 | G52: 31.084 | H52: 34.432 | I52: 150.453 | J52: 250.19 | K52: 38.44 | L52: =L48*L53 -> 38.474298 | M52: =M48*M53 -> 41.341198 | N52: =N48*N53 -> 41.892263 | O52: =SUM(K52:N52) -> 160.14776 | P52: =P48*P53 -> 39.635925 | Q52: =Q48*Q53 -> 42.284033 | R52: =R48*R53 -> 45.247901 | S52: =S48*S53 -> 45.454284 | T52: =SUM(P52:S52) -> 172.62214 | U52: =U48*U53 -> 192.93844 | V52: =V48*V53 -> 213.13398 | W52: =W48*W53 -> 232.00317
B53: % tax rate | C53: % | D53: =D52/D48 -> 0.23026361 | E53: =E52/E48 -> 0.24616547 | F53: =F52/F48 -> 0.25075657 | G53: =G52/G48 -> 0.21668874 | H53: =H52/H48 -> 0.21565287 | I53: =I52/I48 -> 1.6766554 | J53: =J52/J48 -> 0.47266393 | K53: =K52/K48 -> 0.24486884 | L53: 0.245 | M53: =L53 -> 0.245 | N53: =M53 -> 0.245 | O53: =O52/O48 -> 0.2449685 | P53: =L53 -> 0.245 | Q53: =P53 -> 0.245 | R53: =Q53 -> 0.245 | S53: =R53 -> 0.245 | T53: =T52/T48 -> 0.24254978 | U53: =L53 -> 0.245 | V53: =U53 -> 0.245 | W53: =V53 -> 0.245
A55: x | B55: Net Income | C55: $ | D55: =D48-D52 -> 345.355 | E55: =E48-E52 -> 387.137 | F55: =F48-F52 -> 102.25 | G55: =G48-G52 -> 112.366 | H55: =H48-H52 -> 125.232 | I55: =I48-I52 -> -60.719 | J55: =J48-J52 -> 279.129 | K55: =K48-K52 -> 118.542 | ... W55: =W48-W52 -> 714.94853
B56: % y/y change | C56: % | D56: 0 | E56: =E55/D55-1 -> 0.12098276 | F56: 0 | G56: 0 | H56: 0 | I56: 0 | J56: =J55/E55-1 -> -0.27899167 | K56: =K55/F55-1 -> 0.15933496 | L56: =L55/G55-1 -> 0.055155956 | M56: =M55/H55-1 -> 0.01729898 | N56: =N55/I55-1 -> -3.1261313 | O56: =O55/J55-1 -> 0.76836017 | P56: =P55/K55-1 -> 0.030380453 | Q56: =Q55/L55-1 -> 0.099020244 | ... T56: =T55/O55-1 -> 0.0921292 | U56: =U55/T55-1 -> 0.10293504 | V56: =V55/U55-1 -> 0.10467347 | W56: =W55/V55-1 -> 0.088532051
A58: x | B58: Adjusted Operating Income
B59: Net Income | C59: $ | D59: =D55 -> 345.355 | E59: =E55 -> 387.137 | F59: =F55 -> 102.25 | G59: =G55 -> 112.366 | H59: =H55 -> 125.232 | I59: =I55 -> -60.719 | J59: =J55 -> 279.129 | K59: =K55 -> 118.542 | ... W59: =W55 -> 714.94853
B60: Amortization of debenture synthetic discount | C60: $ | D60: =D29 -> 3.0372471 | E60: =E29 -> 1.517 | F60: =F29 -> 0 | G60: =G29 -> 0 | H60: =H29 -> 0 | I60: =I29 -> 0 | J60: =J29 -> 0 | K60: =K29 -> 0 | ... N60: =N29 -> 0 | O60: =SUM(K60:N60) -> 0 | P60: =P29 -> 0 | Q60: =Q29 -> 0 | R60: =R29 -> 0 | S60: =S29 -> 0 | T60: =SUM(P60:S60) -> 0 | U60: =U29 -> 0 | V60: =V29 -> 0 | W60: =W29 -> 0
B61: Share-based Compensation | C61: $ | D61: =D32 -> 36.470671 | E61: =E32 -> 43.435 | F61: =F32 -> 10.183 | G61: =G32 -> 10.333 | H61: =H32 -> 8.252 | I61: =I32 -> 10.75 | J61: =J32 -> 39.518 | K61: =K32 -> 9.335 | ... N61: =N32 -> 11.931074 | O61: =SUM(K61:N61) -> 43.997827 | P61: =P32 -> 11.28846 | Q61: =Q32 -> 12.042651 | R61: =R32 -> 12.886772 | S61: =S32 -> 12.945551 | T61: =SUM(P61:S61) -> 49.163434 | U61: =U32 -> 53.398267 | V61: =V32 -> 58.003183 | W61: =W32 -> 62.305669
B62: Amortization of intangibles from acquisitions | C62: $ | D62: =D39 -> 27.903412 | E62: =E39 -> 28.734 | F62: =F39 -> 7.799 | G62: =G39 -> 7.829 | H62: =H39 -> 7.831 | I62: =I39 -> 7.823 | J62: =J39 -> 31.282 | K62: =K39 -> 8.979 | ... N62: =N39 -> 9.44975 | O62: =SUM(K62:N62) -> 36.432945 | P62: =P39 -> 8.9407817 | Q62: =Q39 -> 9.5381226 | R62: =R39 -> 10.20669 | S62: =S39 -> 10.253245 | T62: =SUM(P62:S62) -> 38.938839 | U62: =U39 -> 42.292948 | V62: =V39 -> 45.940172 | W62: =W39 -> 49.347863
B63: Gain on investments | C63: $ | D63: =D42 -> 0 | E63: =E42 -> 0 | F63: =F42 -> -3.606 | G63: =G42 -> 0 | H63: =H42 -> 0 | I63: =I42 -> 3.606 | J63: =J42 -> 0 | K63: =K42 -> 0.083 | ... N63: =N42 -> 0 | O63: =SUM(K63:N63) -> 0.083 | P63: =P42 -> 0 | Q63: =Q42 -> 0 | R63: =R42 -> 0 | S63: =S42 -> 0 | T63: =SUM(P63:S63) -> 0 | U63: =U42 -> 0 | V63: =V42 -> 0 | W63: =W42 -> 0
B64: Income Tax Expense | C64: $ | D64: =D52 -> 103.31159 | E64: =E52 -> 126.42 | F64: =F52 -> 34.221 | G64: =G52 -> 31.084 | H64: =H52 -> 34.432 | I64: =I52 -> 150.453 | J64: =J52 -> 250.19 | K64: =K52 -> 38.44 | ... N64: =N52 -> 41.892263 | O64: =SUM(K64:N64) -> 160.14776 | P64: =P52 -> 39.635925 | Q64: =Q52 -> 42.284033 | R64: =R52 -> 45.247901 | S64: =S52 -> 45.454284 | T64: =SUM(P64:S64) -> 172.62214 | U64: =U52 -> 192.93844 | V64: =V52 -> 213.13398 | W64: =W52 -> 232.00317
B65: Strategic initiatives costs - Salaries, wages and benefits | C65: $ | D65: 0 | E65: 5.593 | F65: 0 | G65: 0 | H65: 0 | I65: 5.802 | J65: 5.802 | K65: 4.361 | L65: 0 | M65: 0 | N65: 0 | O65: =SUM(K65:N65) -> 4.361 | P65: 0 | Q65: 0 | R65: 0 | S65: 0 | T65: =SUM(P65:S65) -> 0 | U65: 0 | V65: 0 | W65: 0
B66: Strategic initiatives costs - General and administrative expenses | C66: $ | D66: 0 | E66: 7.806 | F66: 0 | G66: 0 | H66: 2.004 | I66: 7.646 | J66: 9.65 | K66: 2.203 | L66: 0 | M66: 0 | N66: 0 | O66: =SUM(K66:N66) -> 2.203 | P66: 0 | Q66: 0 | R66: 0 | S66: 0 | T66: =SUM(P66:S66) -> 0 | U66: 0 | V66: 0 | W66: 0
B67: Strategic initiatives costs - Depreciation and Amortization | C67: $ | D67: 0 | E67: 0 | F67: 0 | G67: 0 | H67: 0 | I67: 54.09 | J67: 54.09 | K67: 0 | L67: 0 | M67: 0 | N67: 0 | O67: =SUM(K67:N67) -> 0 | P67: 0 | Q67: 0 | R67: 0 | S67: 0 | T67: =SUM(P67:S67) -> 0 | U67: 0 | V67: 0 | W67: 0
B68: Share loss from JV | C68: $ | D68: =D45 -> 0.50892409 | E68: =E45 -> 0.588 | F68: =F45 -> 0 | G68: =G45 -> 0.238 | H68: =H45 -> -0.087 | I68: =I45 -> -3.932 | J68: =J45 -> -3.781 | K68: =K45 -> 0 | ... N68: =N45 -> 0 | O68: =SUM(K68:N68) -> 0 | P68: =P45 -> 0 | Q68: =Q45 -> 0 | R68: =R45 -> 0 | S68: =S45 -> 0 | T68: =SUM(P68:S68) -> 0 | U68: =U45 -> 0 | V68: =V45 -> 0 | W68: =W45 -> 0
A69: x | B69: Adjusted Operating Income | C69: $ | D69: =D59+D60+D61+D62+D63+D64+D65+D66+D67+D68 -> 516.58684 | E69: =E59+E60+E61+E62+E63+E64+E65+E66+E67+E68 -> 601.23 | F69: =F59+F60+F61+F62+F63+F64+F65+F66+F67+F68 -> 150.847 | G69: =G59+G60+G61+G62+G63+G64+G65+G66+G67+G68 -> 161.85 | H69: =H59+H60+H61+H62+H63+H64+H65+H66+H67+H68 -> 177.664 | I69: =I59+I60+I61+I62+I63+I64+I65+I66+I67+I68 -> 175.519 | J69: =J59+J60+J61+J62+J63+J64+J65+J66+J67+J68 -> 665.88 | K69: =K59+K60+K61+K62+K63+K64+K65+K66+K67+K68 -> 181.943 | ... W69: =W59+W60+W61+W62+W63+W64+W65+W66+W67+W68 -> 1058.6052
B70: % y/y change | C70: % | D70: 0 | E70: =E69/D69-1 -> 0.16385078 | F70: 0 | G70: 0 | H70: 0 | I70: 0 | J70: =J69/E69-1 -> 0.10752956 | K70: =K69/F69-1 -> 0.20614265 | L70: =L69/G69-1 -> 0.091593004 | M70: =M69/H69-1 -> 0.068529118 | N70: =N69/I69-1 -> 0.096004723 | O70: =O69/J69-1 -> 0.11255202 | P70: =P69/K69-1 -> 0.00036014695 | Q70: =Q69/L69-1 -> 0.099020244 | ... T70: =T69/O69-1 -> 0.079605604 | U70: =U69/T69-1 -> 0.10426983 | V70: =V69/U69-1 -> 0.10267596 | W70: =W69/V69-1 -> 0.086999887
B71: % margin | C71: % | D71: =D69/D17 -> 0.53884076 | E71: =E69/E17 -> 0.55282467 | F71: =F69/F17 -> 0.54719938 | G71: =G69/G17 -> 0.55805342 | H71: =H69/H17 -> 0.57986227 | I71: =I69/I17 -> 0.56000676 | J71: =J69/J17 -> 0.56168231 | K71: =K69/K17 -> 0.56239259 | ... W71: =W69/W17 -> 0.59237974
B73: Cash Flow Items
B75: Current Operating Assets
B76: Accounts receivable and other current assets | D76: 202.92459 | E76: 202.168 | F76: 185.132 | G76: 248.404 | H76: 213.511 | I76: 245.09 | J76: 245.09 | K76: 250.255 | L76: =L78*'Revenue Build'!L41 -> 247.45153 | M76: =M78*'Revenue Build'!M41 -> 255.22021 | N76: =N78*'Revenue Build'!N41 -> 251.92788 | O76: =O78*'Revenue Build'!O41 -> 251.92788 | P76: =P78*'Revenue Build'!P41 -> 252.16564 | Q76: =Q78*'Revenue Build'!Q41 -> 265.71294 | R76: =R78*'Revenue Build'!R41 -> 273.07319 | S76: =S78*'Revenue Build'!S41 -> 269.19386 | ... W76: =W78*'Revenue Build'!W41 -> 319.76209
B77: Total Current Assets | D77: =D76 -> 202.92459 | E77: =E76 -> 202.168 | F77: =F76 -> 185.132 | G77: =G76 -> 248.404 | H77: =H76 -> 213.511 | I77: =I76 -> 245.09 | J77: =J76 -> 245.09 | K77: =K76 -> 250.255 | ... W77: =W76 -> 319.76209
B78: Accounts receivable - % of Net Earning Assets | C78: % | E78: =E76/'Revenue Build'!E41 -> 0.027306258 | F78: =F76/'Revenue Build'!F41 -> 0.024434381 | G78: =G76/'Revenue Build'!G41 -> 0.029963698 | H78: =H76/'Revenue Build'!H41 -> 0.024288989 | I78: =I76/'Revenue Build'!I41 -> 0.02767747 | J78: =J76/'Revenue Build'!J41 -> 0.02767747 | K78: =K76/'Revenue Build'!K41 -> 0.02965282 | L78: =$J$78 -> 0.02767747 | M78: =L78 -> 0.02767747 | N78: =M78 -> 0.02767747 | O78: =N78 -> 0.02767747 | P78: =O78 -> 0.02767747 | Q78: =P78 -> 0.02767747 | R78: =Q78 -> 0.02767747 | S78: =R78 -> 0.02767747 | T78: =S78 -> 0.02767747 | ... W78: =V78 -> 0.02767747
B79: Current Operating Liabilities
B80: Accounts payable and accrued liabilities | D80: 1208.2584 | E80: 1338.188 | F80: 1228.332 | G80: 1362.461 | H80: 1476.949 | I80: 1249.173 | J80: 1249.173 | K80: 1102.559 | L80: =L82*'Revenue Build'!L41 -> 1261.2092 | M80: =M82*'Revenue Build'!M41 -> 1300.8046 | N80: =N82*'Revenue Build'!N41 -> 1284.0243 | O80: =O82*'Revenue Build'!O41 -> 1284.0243 | P80: =P82*'Revenue Build'!P41 -> 1285.2361 | Q80: =Q82*'Revenue Build'!Q41 -> 1354.2838 | R80: =R82*'Revenue Build'!R41 -> 1391.7976 | S80: =S82*'Revenue Build'!S41 -> 1372.0254 | ... W80: =W82*'Revenue Build'!W41 -> 1629.7612
B81: Total Current Liabilities | D81: =D80 -> 1208.2584 | E81: =E80 -> 1338.188 | F81: =F80 -> 1228.332 | G81: =G80 -> 1362.461 | H81: =H80 -> 1476.949 | I81: =I80 -> 1249.173 | J81: =J80 -> 1249.173 | K81: =K80 -> 1102.559 | ... W81: =W80 -> 1629.7612
B82: Accounts payable - % of Net Earning Assets | C82: % | E82: =E80/'Revenue Build'!E41 -> 0.18074526 | F82: =F80/'Revenue Build'!F41 -> 0.16211963 | G82: =G80/'Revenue Build'!G41 -> 0.16434667 | H82: =H80/'Revenue Build'!H41 -> 0.16801757 | I82: =I80/'Revenue Build'!I41 -> 0.14106633 | J82: =J80/'Revenue Build'!J41 -> 0.14106633 | K82: =K80/'Revenue Build'!K41 -> 0.13064268 | L82: =$J$82 -> 0.14106633 | M82: =L82 -> 0.14106633 | N82: =M82 -> 0.14106633 | O82: =N82 -> 0.14106633 | P82: =O82 -> 0.14106633 | Q82: =P82 -> 0.14106633 | R82: =Q82 -> 0.14106633 | S82: =R82 -> 0.14106633 | T82: =S82 -> 0.14106633 | ... W82: =V82 -> 0.14106633
B83: Net Working Capital | D83: =D76-D80 -> -1005.3338 | E83: =E76-E80 -> -1136.02 | F83: =F76-F80 -> -1043.2 | G83: =G76-G80 -> -1114.057 | H83: =H76-H80 -> -1263.438 | I83: =I76-I80 -> -1004.083 | J83: =J76-J80 -> -1004.083 | K83: =K76-K80 -> -852.304 | ... W83: =W76-W80 -> -1309.9991
B84: % sales | D84: =-D83/D13 -> 2.0009359 | E84: =-E83/E13 -> 1.9075461 | J84: =-J83/J13 -> 1.6120732 | O84: =-O83/O13 -> 1.5154039 | T84: =-T83/T13 -> 1.4588823 | U84: =-U83/U13 -> 1.4006027 | V84: =-V83/V13 -> 1.3446875 | W84: =-W83/W13 -> 1.2953626
B87: Change in Net working Capital | D87: 0 | E87: =E83-D83 -> -130.68617 | F87: =F83-E83 -> 92.82 | G87: =G83-F83 -> -70.857 | H87: =H83-G83 -> -149.381 | I87: =I83-H83 -> 259.355 | J87: =J83-E83 -> 131.937 | K87: =K83-J83 -> 151.779 | L87: =L83-K83 -> -161.4537 | M87: =M83-L83 -> -31.826671 | N87: =N83-M83 -> 13.487984 | O87: =O83-J83 -> -28.013384 | P87: =P83-O83 -> -0.97403592 | Q87: =Q83-P83 -> -55.500483 | R87: =R83-Q83 -> -30.153453 | S87: =S83-R83 -> 15.89284 | T87: =T83-O83 -> -70.735132 | U87: =U83-T83 -> -75.490389 | V87: =V83-U83 -> -68.226956 | W87: =W83-V83 -> -63.450227
B89: Capital Expenditures | O89: 80 | T89: 80 | U89: =T89 -> 80 | V89: 80 | W89: 80
B90: % y/y change | T90: =T89/O89-1 -> 0 | U90: =U89/T89-1 -> 0 | V90: =V89/U89-1 -> 0 | W90: =W89/V89-1 -> 0
A92: x | B92: Adjusted Net Income | D92: =D69*(1-D53) -> 397.63569 | E92: =E69*(1-E53) -> 453.22793 | F92: =F69*(1-F53) -> 113.02112 | G92: =G69*(1-G53) -> 126.77893 | H92: =H69*(1-H53) -> 139.35025 | I92: =I69*(1-0.245) -> 132.51685 | J92: =SUM(F92:I92) -> 511.66714 | K92: =K69*(1-K53) -> 137.39083 | L92: =L69*(1-L53) -> 133.38912 | M92: =M69*(1-M53) -> 143.32856 | N92: =N69*(1-N53) -> 145.23909 | O92: =SUM(K92:N92) -> 559.3476 | P92: =P69*(1-P53) -> 137.41644 | Q92: =Q69*(1-Q53) -> 146.59734 | R92: =R69*(1-R53) -> 156.87297 | S92: =S69*(1-S53) -> 157.58849 | T92: =SUM(P92:S92) -> 598.47525 | U92: =U69*(1-U53) -> 666.81227 | V92: =V69*(1-V53) -> 735.27786 | W92: =W69*(1-W53) -> 799.24695
B93: % y/y change | D93: 0 | E93: =E92/D92-1 -> 0.13980698 | F93: 0 | G93: 0 | H93: 0 | I93: 0 | J93: =J92/E92-1 -> 0.12894 | K93: =K92/F92-1 -> 0.2156208 | L93: =L92/G92-1 -> 0.052139503 | M93: =M92/H92-1 -> 0.028549037 | N93: =N92/I92-1 -> 0.096004723 | O93: =O92/J92-1 -> 0.093186468 | P93: =P92/K92-1 -> 0.00018639068 | Q93: =Q92/L92-1 -> 0.099020244 | ... T93: =T92/O92-1 -> 0.069952294 | U93: =U92/T92-1 -> 0.11418522 | V93: =V92/U92-1 -> 0.10267596 | W93: =W92/V92-1 -> 0.086999887
B94: Free Cash Flow | C94: $ | O94: =O55+O26+O39+O32+O29-O87-O89 -> 593.47632 | T94: =T55+T26+T39+T32+T29-T87-T89 -> 695.07682 | U94: =U55+U26+U39+U32+U29-U87-U89 -> 769.55751 | V94: =V55+V26+V39+V32+V29-V87-V89 -> 840.00902 | W94: =W55+W26+W39+W32+W29-W87-W89 -> 907.84328
B95: FCF per Share | C95: $ | O95: =O94/O100 -> 1.4926632 | T95: =T94/T100 -> 1.7486223 | U95: =U94/U100 -> 1.93561 | V95: =V94/V100 -> 2.1128114 | W95: =W94/W100 -> 2.2834298
B96: FCF Margin | C96: % | O96: =O94/O17 -> 0.45210709 | T96: =T94/T17 -> 0.49292894 | U96: =U94/U17 -> 0.5024671 | V96: =V94/V17 -> 0.5049238 | W96: =W94/W17 -> 0.50801559
B98: Shares Outstanding - WAB | D98: 390.29726 | E98: 396.87991 | F98: 403.50234 | G98: 401.66794 | H98: 401.0291 | I98: 399.883 | J98: 401.50928 | K98: 398.12311 | L98: 397.08385 | M98: 397.12356 | N98: 397.16327 | O98: 397.37013 | P98: 397.20299 | Q98: 397.24271 | R98: 397.28243 | S98: 397.32216 | T98: 397.26296 | U98: 397.34203 | V98: 397.34203 | W98: 397.34203
B99: Share Buybacks | O99: 2
B100: Shares Outstanding - WAD | D100: 405.24194 | E100: 404.16446 | F100: 403.68568 | G100: 401.88111 | H100: 401.26701 | I100: 399.883 | J100: 401.69051 | K100: 398.28016 | L100: 397.2807 | M100: 397.3602 | N100: 397.39994 | O100: 397.59559 | P100: 397.43968 | Q100: 397.47942 | R100: 397.51917 | S100: 397.55892 | T100: 397.49968 | U100: 397.5788 | V100: 397.5788 | W100: 397.5788 | Y100: Do a full Share capital build
B101: Adjusted Shares Outstanding - WAD | D101: =D100 -> 405.24194 | E101: =E100 -> 404.16446 | F101: =F100 -> 403.68568 | G101: =G100 -> 401.88111 | H101: =H100 -> 401.26701 | I101: =I100 -> 399.883 | J101: =J100 -> 401.69051 | K101: =K100 -> 398.28016 | L101: 397.2807 | M101: 397.3602 | N101: 397.39994 | O101: 397.59559 | P101: 397.43968 | Q101: 397.47942 | R101: 397.51917 | S101: 397.55892 | T101: 397.49968 | U101: 397.5788 | V101: 397.5788 | W101: 397.5788 | Y101: Need to fix this
B103: Earnings Per Share | D103: =D55/D100 -> 0.85221929 | E103: =E55/E100 -> 0.95786996 | F103: =F55/F100 -> 0.25329112 | G103: =G55/G100 -> 0.27960011 | H103: =H55/H100 -> 0.31209144 | I103: =I55/I100 -> -0.15184191 | J103: =J55/J100 -> 0.69488572 | K103: =K55/K100 -> 0.29763471 | ... W103: =W55/W100 -> 1.7982562
B104: Adjusted Earnings Per Share | D104: =D92/D101 -> 0.98123034 | E104: =E92/E101 -> 1.1213948 | F104: =F92/F101 -> 0.27997308 | G104: =G92/G101 -> 0.31546377 | H104: =H92/H101 -> 0.34727562 | I104: =I92/I101 -> 0.33138904 | J104: =J92/J101 -> 1.2737845 | K104: =K92/K101 -> 0.34496026 | ... W104: =W92/W101 -> 2.0102856
B106: P/E | O106: 18 | T106: 18 | U106: 18 | V106: 18 | W106: 18
B108: Implied Share Price | O108: =O106*O104*O110 -> 35.988846 | T108: =T106*T104*T110 -> 38.515639 | U108: =U106*U104*U110 -> 42.905016 | V108: =V106*V104*V110 -> 47.31033 | W108: =W106*W104*W110 -> 51.426323
A109: x | B109: Current Share Price | O109: 28.86 | T109: 28.86 | U109: 28.86 | V109: 28.86 | W109: 28.86
B110: USD/CAD Exchange Rate | O110: 1.4212 | T110: 1.4212 | U110: 1.4212 | V110: 1.4212 | W110: 1.4212 | Y110: Note on why Stock is trading down below
Y111: I think stock trading down because of macro risk and then they had slightly weaker originations in q4'25 (had a lot of order volume but those usually cobvert in the next quarter), higher rate risk with war and inflation concerns hurts valuation and then obviously they are balance sheet heavy still so could hurt spreads -- they are protected from this because the way they structure their financing and leases has built in escalators so they earn a fixed spread -- otherwise I think just higher fuel costs which hurts transportation companies in general
B112: Need to build out FCF/Share
B113: Share buybacks

Sheet Revenue Build
A2: x | B2: EFN Thesis Build
D4: 365 | E4: 366 | F4: 90 | G4: 91 | H4: 92 | I4: 92 | J4: 365 | K4: 90 | L4: 91 | M4: 92 | N4: 92 | O4: 365 | P4: 90 | Q4: 91 | R4: 92 | S4: 92 | T4: 365 | U4: 366 | V4: 365 | W4: 365
A5: x | B5: Service and other Revenue | C5: Units | D5: 2023 | E5: =D5+1 -> 2024 | F5: Q1'25A | G5: Q2'25A | H5: Q3'25A | I5: Q4'25A | J5: =E5+1 -> 2025 | K5: Q1'26A | L5: Q2'26E | M5: Q3'26E | N5: Q4'26E | O5: =J5+1 -> 2026 | P5: Q1'27E | Q5: Q2'27E | R5: Q3'27E | S5: Q4'27E | T5: =O5+1 -> 2027 | U5: =T5+1 -> 2028 | V5: =U5+1 -> 2029 | W5: =V5+1 -> 2030 | Y5: Step
B7: EFN Total Fleet TAM | C7: # | D7: =D13+D16 -> 16.662992 | E7: =E13+E16 -> 17.079567 | J7: =J13+J16 -> 17.506556 | K7: =K13+K16 -> 17.614961 | L7: =L13+L16 -> 17.791111 | M7: =M13+M16 -> 17.924544 | N7: =N13+N16 -> 18.058978 | O7: =O13+O16 -> 18.058978 | P7: =P13+P16 -> 18.149273 | Q7: =Q13+Q16 -> 18.330766 | ... W7: =W13+W16 -> 19.938126 | AA7: # of vehicles
B8: % y/y change | C8: % | D8: 0 | E8: =E7/D7-1 -> 0.025 | F8: 0 | G8: 0 | H8: 0 | I8: 0 | J8: =J7/E7-1 -> 0.025 | K8: 0 | L8: =L7/K7-1 -> 0.01 | M8: =M7/L7-1 -> 0.0075 | N8: =N7/M7-1 -> 0.0075 | O8: =O7/J7-1 -> 0.031555146 | P8: =P7/K7-1 -> 0.030332847 | Q8: =Q7/L7-1 -> 0.030332847 | R8: =R7/M7-1 -> 0.027776189 | S8: =S7/N7-1 -> 0.025225876 | T8: =T7/O7-1 -> 0.025225876 | U8: =U7/T7-1 -> 0.025 | V8: =V7/U7-1 -> 0.025 | W8: =W7/V7-1 -> 0.025
B10: EFN Total Fleet SAM | C10: # | D10: =D13 -> 9.607912 | E10: =E13 -> 9.8481098 | J10: =J13+J16 -> 17.506556 | K10: =K13+K16 -> 17.614961 | L10: =L13+L16 -> 17.791111 | M10: =M13+M16 -> 17.924544 | N10: =N13+N16 -> 18.058978 | O10: =O13+O16 -> 18.058978 | P10: =P13+P16 -> 18.149273 | Q10: =Q13+Q16 -> 18.330766 | ... W10: =W13+W16 -> 19.938126
B11: % y/y change | C11: % | D11: 0 | E11: =E10/D10-1 -> 0.025 | F11: 0 | G11: 0 | H11: 0 | I11: 0 | J11: =J10/E10-1 -> 0.77765649 | K11: 0 | L11: =L10/K10-1 -> 0.01 | M11: =M10/L10-1 -> 0.0075 | N11: =N10/M10-1 -> 0.0075 | O11: =O10/J10-1 -> 0.031555146 | P11: =P10/K10-1 -> 0.030332847 | Q11: =Q10/L10-1 -> 0.030332847 | R11: =R10/M10-1 -> 0.027776189 | S11: =S10/N10-1 -> 0.025225876 | T11: =T10/O10-1 -> 0.025225876 | U11: =U10/T10-1 -> 0.025 | V11: =V10/U10-1 -> 0.025 | W11: =W10/V10-1 -> 0.025
B13: Large Fleet TAM, # of vehicles | C13: # | D13: 9.607912 | E13: 9.8481098 | J13: 10.094312 | K13: 10.156819 | L13: =K13*(1+L14) -> 10.258387 | M13: =L13*(1+M14) -> 10.335325 | N13: =M13*(1+N14) -> 10.41284 | O13: =N13 -> 10.41284 | P13: =O13*(1+P14) -> 10.464904 | Q13: =P13*(1+Q14) -> 10.569553 | R13: =Q13*(1+R14) -> 10.622401 | S13: =R13*(1+S14) -> 10.675513 | T13: =S13 -> 10.675513 | U13: =T13*(1+U14) -> 10.942401 | V13: =U13*(1+V14) -> 11.215961 | W13: =V13*(1+W14) -> 11.49636
B14: % y/y change | C14: % | D14: 0 | E14: =E13/D13-1 -> 0.025 | F14: 0 | G14: 0 | H14: 0 | I14: 0 | J14: =J13/E13-1 -> 0.025 | K14: 0 | L14: 0.01 | M14: 0.0075 | N14: 0.0075 | O14: =O13/J13-1 -> 0.031555146 | P14: 0.005 | Q14: 0.01 | R14: 0.005 | S14: 0.005 | T14: =T13/O13-1 -> 0.025225876 | U14: 0.025 | V14: 0.025 | W14: 0.025
B16: SME Fleet TAM, # of vehicles | C16: # | D16: 7.0550803 | E16: 7.2314573 | J16: 7.4122438 | K16: 7.4581422 | L16: =K16*(1+L17) -> 7.5327236 | M16: =L16*(1+M17) -> 7.589219 | N16: =M16*(1+N17) -> 7.6461382 | O16: =N16 -> 7.6461382 | P16: =O16*(1+P17) -> 7.6843689 | Q16: =P16*(1+Q17) -> 7.7612126 | R16: =Q16*(1+R17) -> 7.8000186 | S16: =R16*(1+S17) -> 7.8390187 | T16: =S16 -> 7.8390187 | U16: =T16*(1+U17) -> 8.0349942 | V16: =U16*(1+V17) -> 8.235869 | W16: =V16*(1+W17) -> 8.4417658
B17: % y/y change | C17: % | D17: 0 | E17: =E16/D16-1 -> 0.025 | F17: 0 | G17: 0 | H17: 0 | I17: 0 | J17: =J16/E16-1 -> 0.025 | K17: 0 | L17: 0.01 | M17: 0.0075 | N17: 0.0075 | O17: =O16/J16-1 -> 0.031555146 | P17: 0.005 | Q17: 0.01 | R17: 0.005 | S17: 0.005 | T17: =T16/O16-1 -> 0.025225876 | U17: 0.025 | V17: 0.025 | W17: 0.025
B19: Total Vehicles Under Management (VUM) | C19: # | D19: 1.507 | E19: 1.517 | F19: 1.514 | G19: 1.512 | H19: 1.53 | I19: 1.555 | J19: =I19 -> 1.555 | K19: 1.57 | L19: =K19+(L10*L22) -> 1.5877911 | M19: =L19+(M10*M22) -> 1.5967534 | N19: =M19+(N10*N22) -> 1.6012681 | O19: =N19 -> 1.6012681 | P19: =O19+(P10*P22) -> 1.6103428 | Q19: =P19+(Q10*Q22) -> 1.6378389 | R19: =Q19+(R10*R22) -> 1.6562613 | S19: =R19 -> 1.6562613 | T19: =S19 -> 1.6562613 | U19: =T19+(U10*U22) -> 1.7226822 | V19: =U19+(V10*V22) -> 1.7907636 | W19: =V19+(W10*W22) -> 1.8605471 | AA19: Company annual report
B20: % y/y change | C20: % | D20: 0 | E20: =E19/D19-1 -> 0.0066357001 | F20: 0 | G20: 0 | H20: 0 | I20: 0 | J20: =J19/E19-1 -> 0.02504944 | K20: =K19/F19-1 -> 0.036988111 | L20: =L19/G19-1 -> 0.050126396 | M20: =M19/H19-1 -> 0.043629662 | N20: =N19/I19-1 -> 0.029754423 | O20: =O19/J19-1 -> 0.029754423 | P20: =P19/K19-1 -> 0.025696028 | Q20: =Q19/L19-1 -> 0.031520394 | ... T20: =T19/O19-1 -> 0.034343533 | U20: =U19/T19-1 -> 0.0401029 | V20: =V19/U19-1 -> 0.039520583 | W20: =W19/V19-1 -> 0.038968538 | AA20: management targets 2-4% VUM growth
B21: % of Total SAM | C21: % | D21: =D19/D10 -> 0.1568499 | E21: =E19/E10 -> 0.15403971 | F21: 0 | G21: 0 | H21: 0 | I21: 0 | J21: =J19/J10 -> 0.088823866 | K21: =K19/K10 -> 0.08912878 | L21: =L19/L10 -> 0.089246317 | M21: =M19/M10 -> 0.089081952 | N21: =N19/N10 -> 0.088668811 | O21: =O19/O10 -> 0.088668811 | P21: =P19/P10 -> 0.088727673 | Q21: =Q19/Q10 -> 0.089349181 | ... W21: =W19/W10 -> 0.093316046
B22: % Active SAM Capture Rate | C22: % | D22: 0 | E22: =(E19-D19)/E10 -> 0.0010154233 | F22: 0 | G22: 0 | H22: 0 | I22: 0 | J22: =(J19-E19)/J10 -> 0.0021706154 | K22: =(K19-J19)/K10 -> 0.00085154885 | L22: 0.001 | M22: 0.0005 | N22: 0.00025 | O22: =K22+L22+M22+N22 -> 0.0026015489 | P22: 0.0005 | Q22: 0.0015 | R22: 0.001 | S22: 0.0005 | T22: =SUM(P22:S22) -> 0.0035 | U22: =T22 -> 0.0035 | V22: =U22 -> 0.0035 | W22: =V22 -> 0.0035 | AA22: Driven by conversion of SMEs and continued pentration into large fleets
B24: Average Service Rev per VUM | C24: $ | D24: =D27/D19 -> 333.39867 | E24: =E27/E19 -> 392.57746 | F24: =F27/F19 -> 100.71466 | G24: =G27/G19 -> 100.08995 | H24: =H27/H19 -> 102.0719 | I24: =I27/I19 -> 104.73569 | J24: =J27/J19 -> 400.54791 | K24: =K27/K19 -> 103.26433 | L24: =G24*(1+L25) -> 106.09534 | M24: =H24*(1+M25) -> 109.21693 | N24: =I24*(1+N25) -> 109.97248 | O24: =SUM(K24:N24) -> 428.54908 | P24: =K24*(1+P25) -> 109.46019 | Q24: =L24*(1+Q25) -> 113.52202 | R24: =M24*(1+R25) -> 116.86211 | S24: =N24*(1+S25) -> 116.57082 | T24: =SUM(P24:S24) -> 456.41515 | U24: =T24*(1+U25) -> 488.36421 | V24: =U24*(1+V25) -> 517.66606 | W24: =V24*(1+W25) -> 543.54936
B25: % y/y change | C25: % | D25: 0 | E25: =E24/D24-1 -> 0.17750157 | F25: 0 | G25: 0 | H25: 0 | I25: 0 | J25: =J24/E24-1 -> 0.020302884 | K25: =K24/F24-1 -> 0.025315758 | L25: 0.06 | M25: 0.07 | N25: 0.05 | O25: =O24/J24-1 -> 0.069907166 | P25: 0.06 | Q25: 0.07 | R25: 0.07 | S25: 0.06 | T25: =T24/O24-1 -> 0.065024215 | U25: 0.07 | V25: =U25+$Y$25 -> 0.06 | W25: =V25+$Y$25 -> 0.05 | Y25: -0.01 | AA25: Continued growth in utilization rate as servuces become more important
B27: Service Revenue | C27: $ | D27: 502.43179 | E27: 595.54 | F27: 152.482 | G27: 151.336 | H27: 156.17 | I27: 162.864 | J27: =SUM(F27:I27) -> 622.852 | K27: 162.125 | L27: =L19*L24 -> 168.45724 | M27: =M19*M24 -> 174.3925 | N27: =N19*N24 -> 176.09542 | O27: =SUM(K27:N27) -> 681.07016 | P27: =P19*P24 -> 176.26843 | Q27: =Q19*Q24 -> 185.93078 | R27: =R19*R24 -> 193.5542 | S27: =S19*S24 -> 193.07175 | T27: =T24*T19 -> 755.94276 | U27: =U24*U19 -> 841.29633 | V27: =V24*V19 -> 927.01755 | W27: =W24*W19 -> 1011.2992
B28: % y/y change | C28: % | D28: 0 | E28: =E27/D27-1 -> 0.18531512 | F28: 0 | G28: 0 | H28: 0 | I28: 0 | J28: =J27/E27-1 -> 0.045860899 | K28: =K27/F27-1 -> 0.063240251 | L28: =L27/G27-1 -> 0.11313398 | M28: =M27/H27-1 -> 0.11668374 | N28: =N27/I27-1 -> 0.081242144 | O28: =O27/J27-1 -> 0.093470301 | P28: =P27/K27-1 -> 0.08723779 | Q28: =Q27/L27-1 -> 0.10372682 | ... T28: =T27/O27-1 -> 0.10993375 | U28: =U27/T27-1 -> 0.1129101 | V28: =V27/U27-1 -> 0.10189182 | W28: =W27/V27-1 -> 0.090916965
A30: x | B30: Financing Revenue | C30: Units
B32: Net Earning Assets - BOP | C32: $ | E32: 7610.333 | F32: 7403.724 | G32: 7576.701 | H32: 8290.165 | I32: 8790.444 | J32: 7403.724 | K32: 8855.217 | L32: =K41 -> 8439.501 | M32: =L41 -> 8940.5402 | N32: =M41 -> 9221.2262 | O32: =J41 -> 8855.217 | P32: =O41 -> 9102.2729 | Q32: =P41 -> 9110.8631 | R32: =Q41 -> 9600.3334 | S32: =R41 -> 9866.263 | T32: =O41 -> 9102.2729 | U32: =T41 -> 9726.1007 | V32: =U41 -> 10391.866 | W32: =V41 -> 10993.574
B33: Activations - NEA Change | C33: $ | E33: 6800 | F33: 1500 | G33: 1700 | H33: 1900 | I33: 1600 | J33: =SUM(F33:I33) -> 6700 | K33: 1300 | L33: =L34*L44 -> 1932.2676 | M33: =M34*M44 -> 1756.7378 | N33: =N34*N44 -> 1378.3229 | O33: =SUM(K33:N33) -> 6367.3284 | P33: =P34*P44 -> 1481.909 | Q33: =Q34*Q44 -> 1970.913 | R33: =R34*R44 -> 1791.8726 | S33: =S34*S44 -> 1405.8894 | T33: =SUM(P33:S33) -> 6650.584 | U33: =U34*U44 -> 6783.5957 | V33: =V34*V44 -> 6919.2676 | W33: =W34*W44 -> 7057.6529
B34: % of originations | C34: % | E34: =E33/E44 -> 1.010169 | F34: =F33/F44 -> 0.99412209 | G34: =G33/G44 -> 0.89739123 | H34: =H33/H44 -> 1.1031811 | I34: =I33/I44 -> 1.1840476 | J34: =J33/J44 -> 1.0344554 | K34: =K33/K44 -> 0.89479176 | L34: 1 | M34: =L34 -> 1 | N34: =M34 -> 1 | O34: =O33/O44 -> 0.97655709 | P34: =L34 -> 1 | Q34: =P34 -> 1 | R34: =Q34 -> 1 | S34: =R34 -> 1 | T34: =T33/T44 -> 1 | U34: =T34 -> 1 | V34: =U34 -> 1 | W34: =V34 -> 1
B35: Syndication - NEA Change | C35: $ | E35: -3500 | F35: -600 | G35: -600 | H35: -600 | I35: -700 | J35: =SUM(F35:I35) -> -2500 | K35: -900 | L35: -600 | M35: =L35 -> -600 | N35: =M35 -> -600 | O35: =SUM(K35:N35) -> -2700 | P35: =L35 -> -600 | Q35: =P35 -> -600 | R35: =Q35 -> -600 | S35: =R35 -> -600 | T35: =SUM(P35:S35) -> -2400 | U35: =T35 -> -2400 | V35: =U35 -> -2400 | W35: =V35 -> -2400
B36: Ammoritization - NEA Change | C36: $ | E36: -2100 | F36: -500 | G36: -600 | H36: -600 | I36: -600 | J36: =SUM(F36:I36) -> -2300 | K36: -600 | L36: =-L32*L37*L4/O4 -> -631.22843 | M36: =-M32*M37*M4/O4 -> -676.0518 | N36: =-N32*N37*N4/O4 -> -697.27628 | O36: =SUM(K36:N36) -> -2604.5565 | P36: =-P32*P37*P4/T4 -> -673.31881 | Q36: =-Q32*Q37*Q4/T4 -> -681.44264 | R36: =-R32*R37*R4/T4 -> -725.94302 | S36: =-S32*S37*S4/T4 -> -746.05167 | T36: =SUM(P36:S36) -> -2826.7561 | U36: =-U32*U37*U4/U4 -> -2917.8302 | V36: =-V32*V37*V4/V4 -> -3117.5598 | W36: =-W32*W37*W4/W4 -> -3298.0722
B37: % of NEA BOP | C37: % | E37: =-E36/E32*E4/E4 -> 0.27594062 | F37: =-F36/F32*$J$4/F4 -> 0.27388619 | G37: =-G36/G32*$J$4/G4 -> 0.31763077 | H37: =-H36/H32*$J$4/H4 -> 0.28713961 | I37: =-I36/I32*$J$4/I4 -> 0.27079801 | J37: =-J36/J32*J4/J4 -> 0.31065448 | K37: =-K36/K32*O4/K4 -> 0.27479093 | L37: 0.3 | M37: =L37 -> 0.3 | N37: =M37 -> 0.3 | O37: =-O36/O32*O4/O4 -> 0.29412679 | P37: =L37 -> 0.3 | Q37: =P37 -> 0.3 | R37: =Q37 -> 0.3 | S37: =R37 -> 0.3 | T37: =-T36/T32*T4/T4 -> 0.31055498 | U37: =P37 -> 0.3 | V37: =U37 -> 0.3 | W37: =V37 -> 0.3
B38: Disposition - NEA Change | C38: $ | E38: -1000 | F38: -200 | G38: -200 | H38: -200 | I38: -300 | J38: =SUM(F38:I38) -> -900 | K38: -300 | L38: -200 | M38: =L38 -> -200 | N38: =M38 -> -200 | O38: =SUM(K38:N38) -> -900 | P38: =L38 -> -200 | Q38: =P38 -> -200 | R38: =Q38 -> -200 | S38: =R38 -> -200 | T38: =SUM(P38:S38) -> -800 | U38: =T38 -> -800 | V38: =U38 -> -800 | W38: =V38 -> -800
B39: FX - NEA Change | C39: $ | E39: -400 | F39: 0 | G39: 400 | H39: 0 | I39: 100 | J39: =SUM(F39,G39,H39,I39) -> 500 | K39: 0 | L39: 0 | M39: 0 | N39: 0 | O39: =SUM(K39,L39,M39,N39) -> 0 | P39: 0 | Q39: 0 | R39: 0 | S39: 0 | T39: =SUM(P39,Q39,R39,S39) -> 0 | U39: 0 | V39: 0 | W39: 0
B40: Rounding (Calculated) | C40: $ | E40: -6.609 | F40: -27.023 | G40: 13.464 | H40: 0.279 | I40: -35.227 | J40: =SUM(F40:I40) -> -48.507 | K40: 84.284 | L40: 0 | M40: 0 | N40: 0 | O40: =SUM(K40,L40,M40,N40) -> 84.284 | P40: 0 | Q40: 0 | R40: 0 | S40: 0 | T40: =SUM(P40,Q40,R40,S40) -> 0 | U40: 0 | V40: 0 | W40: 0
B41: Net Earning Assets - EOP | C41: $ | E41: =E32+E33+E35+E36+E38+E39+E40 -> 7403.724 | F41: =F32+F33+F35+F36+F38+F39+F40 -> 7576.701 | G41: =G32+G33+G35+G36+G38+G39+G40 -> 8290.165 | H41: =H32+H33+H35+H36+H38+H39+H40 -> 8790.444 | I41: =I32+I33+I35+I36+I38+I39+I40 -> 8855.217 | J41: =J32+J33+J35+J36+J38+J39+J40 -> 8855.217 | K41: =K32+K33+K35+K36+K38+K39+K40 -> 8439.501 | L41: =L32+L33+L35+L36+L38+L39+L40 -> 8940.5402 | ... W41: =W32+W33+W35+W36+W38+W39+W40 -> 11553.155
B42: Avg. Net Earning Assets | C42: $ | E42: 7980.144 | F42: 7618.35 | G42: 7987.751 | H42: 8532.704 | I42: 8793.408 | J42: 8233.053 | K42: 8839.618 | L42: =AVERAGE(L32,L41) -> 8690.0206 | M42: =AVERAGE(M32,M41) -> 9080.8832 | N42: =AVERAGE(N32,N41) -> 9161.7495 | O42: =(K42*K4+L42*L4+M42*M4+N42*N4)/O4 -> 8944.328 | P42: =AVERAGE(P32,P41) -> 9106.568 | Q42: =AVERAGE(Q32,Q41) -> 9355.5982 | R42: =AVERAGE(R32,R41) -> 9733.2982 | S42: =AVERAGE(S32,S41) -> 9796.1818 | T42: =(P42*P4+Q42*Q4+R42*R4+S42*S4)/T4 -> 9500.4458 | U42: =AVERAGE(U32,U41) -> 10058.983 | V42: =AVERAGE(V32,V41) -> 10692.72 | W42: =AVERAGE(W32,W41) -> 11273.364
B44: Originations | C44: $ | D44: GRAB HISTORICAL ORIGINATIONS TO SHOW GROWTH | E44: 6731.547 | F44: 1508.869 | G44: 1894.38 | H44: 1722.292 | I44: 1351.297 | J44: 6476.838 | K44: 1452.852 | L44: =G44*(1+L45) -> 1932.2676 | M44: =H44*(1+M45) -> 1756.7378 | N44: =I44*(1+N45) -> 1378.3229 | O44: =SUM(K44:N44) -> 6520.1804 | P44: =K44*(1+P45) -> 1481.909 | Q44: =L44*(1+Q45) -> 1970.913 | R44: =M44*(1+R45) -> 1791.8726 | S44: =N44*(1+S45) -> 1405.8894 | T44: =O44*(1+T45) -> 6650.584 | U44: =T44*(1+U45) -> 6783.5957 | V44: =U44*(1+V45) -> 6919.2676 | W44: =V44*(1+W45) -> 7057.6529
B45: % y/y change | C45: % | E45: 0 | F45: 0 | G45: 0 | H45: 0 | I45: 0 | J45: =J44/E44-1 -> -0.037838108 | K45: =K44/F44-1 -> -0.037125158 | L45: 0.02 | M45: =L45 -> 0.02 | N45: =M45 -> 0.02 | O45: =O44/J44-1 -> 0.0066919043 | P45: =L45 -> 0.02 | Q45: =P45 -> 0.02 | R45: =Q45 -> 0.02 | S45: =R45 -> 0.02 | T45: =AVERAGE(P45:S45) -> 0.02 | U45: =T45 -> 0.02 | V45: =U45 -> 0.02 | W45: =V45 -> 0.02
B47: Interest Income Yield | C47: % | E47: =E50/E42*E4/E4 -> 0.078768378 | F47: =F50/F42*$J$4/F4 -> 0.078106582 | G47: =G50/G42*$J$4/G4 -> 0.077997288 | H47: =H50/H42*$J$4/H4 -> 0.074957144 | I47: =I50/I42*$J$4/I4 -> 0.068018677 | J47: =J50/J42*J4/J4 -> 0.074579989 | K47: =K50/K42*$O$4/K4 -> 0.070151756 | L47: 0.07 | M47: =L47 -> 0.07 | N47: =M47 -> 0.07 | O47: =O50/O42*O4/O4 -> 0.070036981 | P47: =O47 -> 0.070036981 | Q47: =P47 -> 0.070036981 | R47: =Q47 -> 0.070036981 | S47: =R47 -> 0.070036981 | T47: =T50/T42*T4/T4 -> 0.070036981 | U47: =T47 -> 0.070036981 | V47: =U47 -> 0.070036981 | W47: =V47 -> 0.070036981
B48: Rental Revenue Yield | C48: % | E48: =E53/E42*$E$4/E4 -> 0.11244296 | F48: =F53/F42*$J$4/F4 -> 0.11884766 | G48: =G53/G42*$J$4/G4 -> 0.12294657 | H48: =H53/H42*$J$4/H4 -> 0.11817778 | I48: =I53/I42*$J$4/I4 -> 0.11678289 | J48: =J53/J42*J4/J4 -> 0.11916661 | K48: =K53/K42*O4/K4 -> 0.13017428 | L48: 0.13 | M48: =L48 -> 0.13 | N48: =M48 -> 0.13 | O48: =O53/O42*O4/O4 -> 0.13004247 | P48: =O48 -> 0.13004247 | Q48: =P48 -> 0.13004247 | R48: =Q48 -> 0.13004247 | S48: =R48 -> 0.13004247 | T48: =T53/T42*T4/T4 -> 0.13004247 | U48: =T48 -> 0.13004247 | V48: =U48 -> 0.13004247 | W48: =V48 -> 0.13004247
B50: Interest Income | C50: $ | D50: 521.50274 | E50: 628.583 | F50: 146.723 | G50: 155.329 | H50: 161.211 | I50: 150.758 | J50: =SUM(F50:I50) -> 614.021 | K50: 152.905 | L50: =L42*L47*L4/$O$4 -> 151.65872 | M50: =M42*M47*M4/$O$4 -> 160.22161 | N50: =N42*N47*N4/$O$4 -> 161.6484 | O50: =SUM(K50:N50) -> 626.43373 | P50: =P42*P47*P4/$T$4 -> 157.2649 | Q50: =Q42*Q47*Q4/$T$4 -> 163.36067 | R50: =R42*R47*R4/$T$4 -> 171.82344 | S50: =S42*S47*S4/$T$4 -> 172.93354 | T50: =SUM(P50:S50) -> 665.38254 | U50: =U42*U47*U4/U4 -> 704.50083 | V50: =V42*V47*V4/V4 -> 748.88583 | W50: =W42*W47*W4/W4 -> 789.5524
B51: % y/y change | C51: % | D51: 0 | E51: =E50/D50-1 -> 0.20533019 | F51: 0 | G51: 0 | H51: 0 | I51: 0 | J51: =J50/E50-1 -> -0.023166392 | K51: =K50/F50-1 -> 0.042133817 | L51: =L50/G50-1 -> -0.023629101 | M51: =M50/H50-1 -> -0.0061372351 | N51: =N50/I50-1 -> 0.072237644 | O51: =O50/J50-1 -> 0.020215479 | P51: =P50/K50-1 -> 0.028513768 | Q51: =Q50/L50-1 -> 0.077159799 | ... T51: =T50/O50-1 -> 0.062175477 | U51: =U50/T50-1 -> 0.058790676 | V51: =V50/U50-1 -> 0.063002051 | W51: =W50/V50-1 -> 0.054302763
B53: Rental Revenue | C53: $ | D53: 803.28445 | E53: 897.311 | F53: 223.255 | G53: 244.844 | H53: 254.166 | I53: 258.84 | J53: 981.105 | K53: 283.732 | L53: =L48*L42*L4/$O$4 -> 281.6519 | M53: =M48*M42*M4/$O$4 -> 297.55442 | N53: =N48*N42*N4/$O$4 -> 300.20418 | O53: =SUM(K53:N53) -> 1163.1425 | P53: =P48*P42*P4/$T$4 -> 292.00453 | Q53: =Q48*Q42*Q4/$T$4 -> 303.32297 | R53: =R48*R42*R4/$T$4 -> 319.03637 | S53: =S48*S42*S4/$T$4 -> 321.09756 | T53: =SUM(P53:S53) -> 1235.4614 | U53: =U48*U42*U4/U4 -> 1308.095 | V53: =V48*V42*V4/V4 -> 1390.5077 | W53: =W48*W42*W4/W4 -> 1466.0161
B54: % y/y change | C54: % | D54: 0 | E54: =E53/D53-1 -> 0.11705261 | F54: 0 | G54: 0 | H54: 0 | I54: 0 | J54: =J53/E53-1 -> 0.093383453 | K54: =K53/F53-1 -> 0.27088755 | L54: =L53/G53-1 -> 0.15033205 | M54: =M53/H53-1 -> 0.17070898 | N54: =N53/I53-1 -> 0.15980597 | O54: =O53/J53-1 -> 0.18554334 | P54: =P53/K53-1 -> 0.029156135 | Q54: =Q53/L53-1 -> 0.076942744 | ... T54: =T53/O53-1 -> 0.062175477 | U54: =U53/T53-1 -> 0.058790676 | V54: =V53/U53-1 -> 0.063002051 | W54: =W53/V53-1 -> 0.054302763
B56: Depreciation of equipment under operating leases | C56: $ | D56: -483.40159 | E56: -523.44 | F56: -130.208 | G56: -140.554 | H56: -150.066 | I56: -152.284 | J56: =SUM(F56:I56) -> -573.112 | K56: -170.106 | L56: =K56 -> -170.106 | M56: =L56 -> -170.106 | N56: =M56 -> -170.106 | O56: =SUM(K56:N56) -> -680.424 | P56: =K56+$Y$56/4 -> -180.106 | Q56: =L56+$Y$56/4 -> -180.106 | R56: =M56+$Y$56/4 -> -180.106 | S56: =N56+$Y$56/4 -> -180.106 | T56: =SUM(P56:S56) -> -720.424 | U56: =T56+$Y$56 -> -760.424 | V56: =U56+$Y$56 -> -800.424 | W56: =V56+$Y$56 -> -840.424 | Y56: -40
B57: Interest Expense | C57: $ | D57: -430.67053 | E57: -553.324 | F57: -128.214 | G57: -132.537 | H57: -135.103 | I57: -127.843 | J57: =SUM(F57:I57) -> -523.697 | K57: -129.013 | L57: =-'Debt Build'!L10*'Debt Build'!L13*'Debt Build'!L4/'Debt Build'!$O$4 -> -138.96393 | M57: =-'Debt Build'!M10*'Debt Build'!M13*'Debt Build'!M4/'Debt Build'!$O$4 -> -146.06402 | N57: =-'Debt Build'!N10*'Debt Build'!N13*'Debt Build'!N4/'Debt Build'!$O$4 -> -147.36474 | O57: =SUM(K57:N57) -> -561.40569 | P57: =-'Debt Build'!P10*'Debt Build'!P13*'Debt Build'!P4/'Debt Build'!$O$4 -> -143.29287 | Q57: =-'Debt Build'!Q10*'Debt Build'!Q13*'Debt Build'!Q4/'Debt Build'!$O$4 -> -148.84707 | R57: =-'Debt Build'!R10*'Debt Build'!R13*'Debt Build'!R4/'Debt Build'!$O$4 -> -156.55797 | S57: =-'Debt Build'!S10*'Debt Build'!S13*'Debt Build'!S4/'Debt Build'!$O$4 -> -157.56944 | T57: =SUM(P57:S57) -> -606.26735 | U57: =-'Debt Build'!U10*'Debt Build'!U13*'Debt Build'!U4/'Debt Build'!U4 -> -641.91022 | V57: =-'Debt Build'!V10*'Debt Build'!V13*'Debt Build'!V4/'Debt Build'!V4 -> -682.35188 | W57: =-'Debt Build'!W10*'Debt Build'!W13*'Debt Build'!W4/'Debt Build'!W4 -> -719.40548
B59: Net Financing Revenue | C59: $ | D59: =D50+D53+D56+D57 -> 410.71508 | E59: =E50+E53+E56+E57 -> 449.13 | F59: =F50+F53+F56+F57 -> 111.556 | G59: =G50+G53+G56+G57 -> 127.082 | H59: =H50+H53+H56+H57 -> 130.208 | I59: =I50+I53+I56+I57 -> 129.471 | J59: =J50+J53+J56+J57 -> 498.317 | K59: =K50+K53+K56+K57 -> 137.518 | ... W59: =W50+W53+W56+W57 -> 695.73906
B60: % y/y change | C60: % | D60: 0 | E60: =E59/D59-1 -> 0.093531806 | F60: 0 | G60: 0 | H60: 0 | I60: 0 | J60: =J59/E59-1 -> 0.10951618 | K60: =K59/F59-1 -> 0.23272616 | L60: =L59/G59-1 -> -0.022358153 | M60: =M59/H59-1 -> 0.087536932 | N60: =N59/I59-1 -> 0.11516742 | O60: =O59/J59-1 -> 0.099192947 | P60: 0.05 | Q60: 0.06 | R60: 0.07 | S60: 0.05 | T60: =T59/O59-1 -> 0.0482086 | U60: =U59/T59-1 -> 0.062891003 | V60: =V59/U59-1 -> 0.075960873 | W60: =W59/V59-1 -> 0.059580165
A62: x | B62: Syndication Revenue
B64: Syndication Revenue | C64: $ | D64: 45.553521 | E64: 42.89 | F64: 11.633 | G64: 11.608 | H64: 20.012 | I64: 21.088 | J64: =SUM(F64:I64) -> 64.341 | K64: 23.873 | L64: 20 | M64: =L64 -> 20 | N64: =M64 -> 20 | O64: =SUM(K64:N64) -> 83.873 | P64: =L64 -> 20 | Q64: =P64 -> 20 | R64: =Q64 -> 20 | S64: =R64 -> 20 | T64: =SUM(P64:S64) -> 80 | U64: =T64 -> 80 | V64: =U64 -> 80 | W64: =V64 -> 80
B65: % y/y change | C65: % | D65: 0 | E65: =E64/D64-1 -> -0.058470155 | F65: 0 | G65: 0 | H65: 0 | I65: 0 | J65: =J64/E64-1 -> 0.50013989 | K65: =K64/F64-1 -> 1.0521791 | L65: =L64/G64-1 -> 0.72294969 | M65: =M64/H64-1 -> -0.00059964022 | N65: =N64/I64-1 -> -0.051593323 | O65: =O64/J64-1 -> 0.30357004 | P65: 0.05 | Q65: 0.06 | R65: 0.07 | S65: 0.05 | T65: =T64/O64-1 -> -0.046176958 | U65: =U64/T64-1 -> 0 | V65: =V64/U64-1 -> 0 | W65: =W64/V64-1 -> 0
A67: x | B67: Net Revenue
B69: Service Revenue | C69: $ | D69: =D27 -> 502.43179 | E69: =E27 -> 595.54 | F69: =F27 -> 152.482 | G69: =G27 -> 151.336 | H69: =H27 -> 156.17 | I69: =I27 -> 162.864 | J69: =J27 -> 622.852 | K69: =K27 -> 162.125 | ... W69: =W27 -> 1011.2992
B70: % y/y change | C70: % | D70: 0 | E70: =E69/D69-1 -> 0.18531512 | F70: 0 | G70: 0 | H70: 0 | I70: 0 | J70: =J69/E69-1 -> 0.045860899 | K70: =K69/F69-1 -> 0.063240251 | L70: =L69/G69-1 -> 0.11313398 | M70: =M69/H69-1 -> 0.11668374 | N70: =N69/I69-1 -> 0.081242144 | O70: =O69/J69-1 -> 0.093470301 | P70: 0.05 | Q70: 0.06 | R70: 0.07 | S70: 0.05 | T70: =T69/O69-1 -> 0.10993375 | U70: =U69/T69-1 -> 0.1129101 | V70: =V69/U69-1 -> 0.10189182 | W70: =W69/V69-1 -> 0.090916965
B72: Net Financing Revenue | C72: $ | D72: =D59 -> 410.71508 | E72: =E59 -> 449.13 | F72: =F59 -> 111.556 | G72: =G59 -> 127.082 | H72: =H59 -> 130.208 | I72: =I59 -> 129.471 | J72: =J59 -> 498.317 | K72: =K59 -> 137.518 | ... W72: =W59 -> 695.73906
B73: % y/y change | C73: % | D73: 0 | E73: =E72/D72-1 -> 0.093531806 | F73: 0 | G73: 0 | H73: 0 | I73: 0 | J73: =J72/E72-1 -> 0.10951618 | K73: =K72/F72-1 -> 0.23272616 | L73: =L72/G72-1 -> -0.022358153 | M73: =M72/H72-1 -> 0.087536932 | N73: =N72/I72-1 -> 0.11516742 | O73: =O72/J72-1 -> 0.099192947 | P73: 0.05 | Q73: 0.06 | R73: 0.07 | S73: 0.05 | T73: =T72/O72-1 -> 0.0482086 | U73: =U72/T72-1 -> 0.062891003 | V73: =V72/U72-1 -> 0.075960873 | W73: =W72/V72-1 -> 0.059580165
B75: Syndication Revenue | C75: $ | D75: =D64 -> 45.553521 | E75: =E64 -> 42.89 | F75: =F64 -> 11.633 | G75: =G64 -> 11.608 | H75: =H64 -> 20.012 | I75: =I64 -> 21.088 | J75: =J64 -> 64.341 | K75: =K64 -> 23.873 | ... W75: =W64 -> 80
B76: % y/y change | C76: % | D76: 0 | E76: =E75/D75-1 -> -0.058470155 | F76: 0 | G76: 0 | H76: 0 | I76: 0 | J76: =J75/E75-1 -> 0.50013989 | K76: =K75/F75-1 -> 1.0521791 | L76: =L75/G75-1 -> 0.72294969 | M76: =M75/H75-1 -> -0.00059964022 | N76: =N75/I75-1 -> -0.051593323 | O76: =O75/J75-1 -> 0.30357004 | P76: 0.05 | Q76: 0.06 | R76: 0.07 | S76: 0.05 | T76: =T75/O75-1 -> -0.046176958 | U76: =U75/T75-1 -> 0 | V76: =V75/U75-1 -> 0 | W76: =W75/V75-1 -> 0
B78: Net Revenue | C78: $ | D78: =D69+D72+D75 -> 958.70039 | E78: =E69+E72+E75 -> 1087.56 | F78: =F69+F72+F75 -> 275.671 | G78: =G69+G72+G75 -> 290.026 | H78: =H69+H72+H75 -> 306.39 | I78: =I69+I72+I75 -> 313.423 | J78: =J69+J72+J75 -> 1185.51 | K78: =K69+K72+K75 -> 323.516 | ... W78: =W69+W72+W75 -> 1787.0382
B79: % y/y change | C79: % | D79: 0 | E79: =E78/D78-1 -> 0.13441072 | F79: 0 | G79: 0 | H79: 0 | I79: 0 | J79: =J78/E78-1 -> 0.090063996 | K79: =K78/F78-1 -> 0.17355834 | L79: =L78/G78-1 -> 0.078172044 | M79: =M78/H78-1 -> 0.096636667 | N79: =N78/I78-1 -> 0.086318687 | O79: =O78/J78-1 -> 0.10727847 | P79: 0.05 | Q79: 0.06 | R79: 0.07 | S79: 0.05 | T79: =T78/O78-1 -> 0.074203133 | U79: =U78/T78-1 -> 0.086137867 | V79: =V78/U78-1 -> 0.086237166 | W79: =W78/V78-1 -> 0.074176724
A80: x

Sheet Debt Build
A2: x | B2: EFN Debt Build
D4: 365 | E4: 366 | F4: 90 | G4: 91 | H4: 92 | I4: 92 | J4: 365 | K4: 90 | L4: 91 | M4: 92 | N4: 92 | O4: 365 | P4: 90 | Q4: 91 | R4: 92 | S4: 92 | T4: 365 | U4: 366 | V4: 365 | W4: 365
A5: x | B5: Debt Build | C5: Units | D5: 2023 | E5: =D5+1 -> 2024 | F5: Q1'25A | G5: Q2'25A | H5: Q3'25A | I5: Q4'25A | J5: =E5+1 -> 2025 | K5: Q1'26A | L5: Q2'26E | M5: Q3'26E | N5: Q4'26E | O5: =J5+1 -> 2026 | P5: Q1'27E | Q5: Q2'27E | R5: Q3'27E | S5: Q4'27E | T5: =O5+1 -> 2027 | U5: =T5+1 -> 2028 | V5: =U5+1 -> 2029 | W5: =V5+1 -> 2030
B7: Total debt - BOP, mm | C7: $ | E7: 8064.097 | F7: =E9 -> 8331.106 | G7: =F9 -> 8908.953 | H7: =G9 -> 9296.691 | I7: =H9 -> 9344.838 | J7: =E9 -> 8331.106 | K7: =J9 -> 9538.652 | L7: =K9 -> 9381.099 | M7: =L9 -> 9834.5942 | N7: =M9 -> 10143.349 | O7: =J9 -> 9538.652 | P7: =O9 -> 10012.5 | Q7: =P9 -> 10021.949 | R7: =Q9 -> 10560.367 | S7: =R9 -> 10852.889 | T7: =O9 -> 10012.5 | U7: =T9 -> 10698.711 | V7: =U9 -> 11431.053 | W7: =V9 -> 12092.931
B8: Change in debt, mm | C8: $ | E8: =E9-E7 -> 267.009 | F8: =F9-F7 -> 577.847 | G8: =G9-G7 -> 387.738 | H8: =H9-H7 -> 48.147 | I8: =I9-I7 -> 193.814 | J8: =J9-J7 -> 1207.546 | K8: =K9-K7 -> -157.553 | L8: =L9-L7 -> 453.49519 | ... N8: =N9-N7 -> -130.84868 | O8: =SUM(K8:N8) -> 473.84815 | P8: =P9-P7 -> 9.4492481 | Q8: =Q9-Q7 -> 538.41735 | R8: =R9-R7 -> 292.52254 | S8: =S9-S7 -> -154.17849 | T8: =SUM(P8:S8) -> 686.21064 | U8: =U9-U7 -> 732.342 | V8: =V9-V7 -> 661.8785 | W8: =W9-W7 -> 615.53884
B9: Total debt - EOP, mm | C9: $ | E9: 8331.106 | F9: 8908.953 | G9: 9296.691 | H9: 9344.838 | I9: 9538.652 | J9: =I9 -> 9538.652 | K9: 9381.099 | L9: ='Revenue Build'!L41*L11 -> 9834.5942 | M9: ='Revenue Build'!M41*M11 -> 10143.349 | N9: ='Revenue Build'!N41*N11 -> 10012.5 | O9: =O7+O8 -> 10012.5 | P9: ='Revenue Build'!P41*P11 -> 10021.949 | Q9: ='Revenue Build'!Q41*Q11 -> 10560.367 | R9: ='Revenue Build'!R41*R11 -> 10852.889 | S9: ='Revenue Build'!S41*S11 -> 10698.711 | T9: =T7+T8 -> 10698.711 | U9: ='Revenue Build'!U41*U11 -> 11431.053 | V9: ='Revenue Build'!V41*V11 -> 12092.931 | W9: ='Revenue Build'!W41*W11 -> 12708.47
B10: Avg. debt outstanding, mm | C10: $ | E10: 8473.105 | F10: 8363.864 | G10: 8852.832 | H10: 8954.986 | I10: 8725.152 | J10: 8724.209 | K10: 9018.957 | L10: =AVERAGE(L7,L9) -> 9607.8466 | M10: =AVERAGE(M7,M9) -> 9988.9715 | N10: =AVERAGE(N7,N9) -> 10077.924 | O10: =(K10*K4+L10*L4+M10*M4+N10*N4)/O4 -> 9677.1907 | P10: =AVERAGE(P7,P9) -> 10017.225 | Q10: =AVERAGE(Q7,Q9) -> 10291.158 | R10: =AVERAGE(R7,R9) -> 10706.628 | S10: =AVERAGE(S7,S9) -> 10775.8 | T10: =(P10*P4+Q10*Q4+R10*R4+S10*S4)/T4 -> 10450.49 | U10: =AVERAGE(U7,U9) -> 11064.882 | V10: =AVERAGE(V7,V9) -> 11761.992 | W10: =AVERAGE(W7,W9) -> 12400.701
B11: % Earning Assets | C11: % | E11: =E9/'Revenue Build'!E41 -> 1.1252589 | F11: =F9/'Revenue Build'!F41 -> 1.1758354 | G11: =G9/'Revenue Build'!G41 -> 1.1214121 | H11: =H9/'Revenue Build'!H41 -> 1.0630678 | I11: =I9/'Revenue Build'!I41 -> 1.0771788 | J11: =J9/'Revenue Build'!J41 -> 1.0771788 | K11: =K9/'Revenue Build'!K41 -> 1.1115703 | L11: 1.1 | M11: =L11 -> 1.1 | N11: =M11 -> 1.1 | O11: =O9/'Revenue Build'!O41 -> 1.1 | P11: =O11 -> 1.1 | Q11: =P11 -> 1.1 | R11: =Q11 -> 1.1 | S11: =R11 -> 1.1 | T11: =T9/'Revenue Build'!T41 -> 1.1 | U11: =T11 -> 1.1 | V11: =U11 -> 1.1 | W11: =V11 -> 1.1
A13: x | B13: Effective Interest Expense Rate, % | C13: % | E13: =-'Revenue Build'!E57/'Debt Build'!E10*'Debt Build'!E4/'Debt Build'!E4 -> 0.065303569 | F13: =-'Revenue Build'!F57/'Debt Build'!F10*$J$4/F4 -> 0.06216971 | G13: =-'Revenue Build'!G57/'Debt Build'!G10*$J$4/G4 -> 0.060049084 | H13: =-'Revenue Build'!H57/'Debt Build'!H10*$J$4/H4 -> 0.059855645 | I13: =-'Revenue Build'!I57/'Debt Build'!I10*$J$4/I4 -> 0.05813116 | J13: =-'Revenue Build'!J57/'Debt Build'!J10*'Debt Build'!J4/'Debt Build'!J4 -> 0.060028021 | K13: =-'Revenue Build'!K57/'Debt Build'!K10*$J$4/K4 -> 0.058013292 | L13: =K13 -> 0.058013292 | M13: =L13 -> 0.058013292 | N13: =M13 -> 0.058013292 | O13: =-'Revenue Build'!O57/'Debt Build'!O10*'Debt Build'!O4/'Debt Build'!O4 -> 0.058013292 | P13: =O13 -> 0.058013292 | Q13: =P13 -> 0.058013292 | R13: =Q13 -> 0.058013292 | S13: =R13 -> 0.058013292 | T13: =-'Revenue Build'!T57/'Debt Build'!T10*'Debt Build'!T4/'Debt Build'!T4 -> 0.058013292 | U13: =T13 -> 0.058013292 | V13: =U13 -> 0.058013292 | W13: =V13 -> 0.058013292

Sheet Comps
B2: WIP

Sheet VUM Build -- Ignore
B2: EFN Thesis Build
A4: x | B4: Service and other Revenue | C4: Units | D4: 2023 | E4: =D4+1 -> 2024 | F4: =E4+1 -> 2025 | G4: Q1'26A | H4: Q2'26E | I4: Q3'26E | J4: Q4'26E | K4: =F4+1 -> 2026 | L4: =K4+1 -> 2027 | M4: =L4+1 -> 2028 | N4: =M4+1 -> 2029 | O4: =N4+1 -> 2030
B6: EFN Total Fleet TAM | C6: # | D6: =D12+D15 -> 16.662992 | E6: =E12+E15 -> 17.079567 | F6: =F12+F15 -> 17.506556 | G6: =G12+G15 -> 17.614961 | H6: =H12+H15 -> 17.791111 | I6: =I12+I15 -> 17.924544 | J6: =J12+J15 -> 18.058978 | K6: =K12+K15 -> 18.055335 | ... O6: =O12+O15 -> 19.929712 | Q6: # of vehicles
B7: % y/y change | D7: 0 | E7: =E6/D6-1 -> 0.025 | F7: =F6/E6-1 -> 0.025 | G7: 0 | H7: =H6/G6-1 -> 0.01 | I7: =I6/H6-1 -> 0.0075 | J7: =J6/I6-1 -> 0.0075 | K7: =K6/F6-1 -> 0.031347052 | L7: =L6/K6-1 -> 0.025 | M7: =M6/L6-1 -> 0.025 | N7: =N6/M6-1 -> 0.025 | O7: =O6/N6-1 -> 0.025
B9: EFN Total Fleet SAM | C9: # | D9: =D12 -> 9.607912 | E9: =E12 -> 9.8481098 | F9: =F12+F15 -> 17.506556 | G9: =G12+G15 -> 17.614961 | H9: =H12+H15 -> 17.791111 | I9: =I12+I15 -> 17.924544 | J9: =J12+J15 -> 18.058978 | K9: =K12+K15 -> 18.055335 | L9: =L12+L15 -> 18.506719 | M9: =M12+M15 -> 18.969387 | ... O9: =O12+O15 -> 19.929712
B10: % y/y change | D10: 0 | E10: =E9/D9-1 -> 0.025 | F10: =F9/E9-1 -> 0.77765649 | G10: 0 | H10: =H9/G9-1 -> 0.01 | I10: =I9/H9-1 -> 0.0075 | J10: =J9/I9-1 -> 0.0075 | K10: =K9/F9-1 -> 0.031347052 | L10: =L9/K9-1 -> 0.025 | M10: =M9/L9-1 -> 0.025 | N10: =N9/M9-1 -> 0.025 | O10: =O9/N9-1 -> 0.025
B12: Large Fleet TAM | D12: 9.607912 | E12: 9.8481098 | F12: 10.094312 | G12: 10.156819 | H12: =G12*(1+H13) -> 10.258387 | I12: =H12*(1+I13) -> 10.335325 | J12: =I12*(1+J13) -> 10.41284 | K12: =G12*(1+K13) -> 10.410739 | L12: =K12*(1+L13) -> 10.671008 | M12: =L12*(1+M13) -> 10.937783 | N12: =M12*(1+N13) -> 11.211228 | O12: =N12*(1+O13) -> 11.491508
B13: % y/y change | D13: 0 | E13: =E12/D12-1 -> 0.025 | F13: =F12/E12-1 -> 0.025 | G13: 0 | H13: 0.01 | I13: 0.0075 | J13: 0.0075 | K13: =H13+I13+J13 -> 0.025 | L13: 0.025 | M13: 0.025 | N13: 0.025 | O13: 0.025
B15: SME Fleet TAM | D15: 7.0550803 | E15: 7.2314573 | F15: 7.4122438 | G15: 7.4581422 | H15: =G15*(1+H16) -> 7.5327236 | I15: =H15*(1+I16) -> 7.589219 | J15: =I15*(1+J16) -> 7.6461382 | K15: =G15*(1+K16) -> 7.6445957 | L15: =K15*(1+L16) -> 7.8357106 | M15: =L15*(1+M16) -> 8.0316034 | N15: =M15*(1+N16) -> 8.2323935 | O15: =N15*(1+O16) -> 8.4382033
B16: % y/y change | D16: 0 | E16: =E15/D15-1 -> 0.025 | F16: =F15/E15-1 -> 0.025 | G16: 0 | H16: 0.01 | I16: 0.0075 | J16: 0.0075 | K16: =H16+I16+J16 -> 0.025 | L16: 0.025 | M16: 0.025 | N16: 0.025 | O16: 0.025
B18: Total Vehicles Under Management (VUM) | D18: 1.507 | E18: 1.498 | F18: 1.525 | G18: 1.57
B19: % y/y change | D19: 0 | E19: =E18/D18-1 -> -0.0059721301 | F19: =F18/E18-1 -> 0.018024032 | G19: 0
B20: % of Total SAM | D20: =D18/D9 -> 0.1568499 | E20: =E18/E9 -> 0.15211041 | F20: =F18/F9 -> 0.087110222 | G20: =G18/G9 -> 0.08912878
B22: Large Fleet VUM | G22: 1.455
B23: % y/y change | G23: 0
B24: % of Total VUM | G24: =G22/$G$18 -> 0.92675159
B25: % Active Large Capture | G25: 0.005
B27: SME Fleet VUM
B28: % y/y change | G28: 0
B29: % of Total VUM | G29: =G27/$G$18 -> 0
B30: % Active SME Capture | G30: 0.0025
